packagehelper/__init__.py
packagehelper/_test_assets/__init__.py
packagehelper/_test_assets/test1.txt
packagehelper/_test_assets/test2/__init__.py
packagehelper/_test_assets/test2/test2.txt
packagehelper/packages.py
packagehelper/resources.py
packagehelper-0.1.0.dist-info/LICENSE
packagehelper-0.1.0.dist-info/METADATA
packagehelper-0.1.0.dist-info/WHEEL
packagehelper-0.1.0.dist-info/RECORD
